ritis_inrix_api/Geometry_Scraper.py
ritis_inrix_api/INRIX_API.py
ritis_inrix_api/RITIS_API.py
ritis_inrix_api/__init__.py
ritis_inrix_api-1.0.0.dist-info/licenses/LICENSE
ritis_inrix_api-1.0.0.dist-info/METADATA
ritis_inrix_api-1.0.0.dist-info/WHEEL
ritis_inrix_api-1.0.0.dist-info/top_level.txt
ritis_inrix_api-1.0.0.dist-info/RECORD
