Metadata-Version: 2.4
Name: ritis_inrix_api
Version: 1.0.0
Summary: Automated download of XD Segment data from RITIS or INRIX API, for daily or real time processing.
Author-email: Shawn Strasser <shawn.strasser@odot.oregon.gov>
Classifier: Programming Language :: Python :: 3
Classifier: License :: OSI Approved :: MIT License
Classifier: Operating System :: OS Independent
Requires-Python: >=3.9
License-File: LICENSE
Requires-Dist: requests
Requires-Dist: duckdb
Requires-Dist: pandas
Requires-Dist: pyarrow
Provides-Extra: dev
Requires-Dist: pytest; extra == "dev"
Dynamic: license-file
